mrbles/__init__.py
mrbles/core.py
mrbles/data.py
mrbles/kinetics.py
mrbles/path.py
mrbles/pipeline.py
mrbles/report.py
mrbles-1.0.1.dist-info/LICENSE.txt
mrbles-1.0.1.dist-info/METADATA
mrbles-1.0.1.dist-info/WHEEL
mrbles-1.0.1.dist-info/top_level.txt
mrbles-1.0.1.dist-info/RECORD
