Metadata-Version: 2.1
Name: mrbles
Version: 1.0.1
Summary: MRBLEs decoding and analysis package
Home-page: https://github.com/FordyceLab/MRBLEs
Author: Björn Harink
Author-email: bjorn@harink.info
License: MIT
Requires-Dist: future
Requires-Dist: six
Requires-Dist: numpy (>=1.14.0)
Requires-Dist: scipy
Requires-Dist: pandas (>=0.23.1)
Requires-Dist: xarray
Requires-Dist: opencv-python (>=3.2.0)
Requires-Dist: scikit-learn
Requires-Dist: scikit-image
Requires-Dist: photutils (>=0.6.0)
Requires-Dist: packaging
Requires-Dist: matplotlib
Requires-Dist: plotly
Requires-Dist: lmfit
Requires-Dist: xlrd
Requires-Dist: notebook (>=5.7.8)
Requires-Dist: jupyter
Requires-Dist: seaborn (>=0.9.0)
Requires-Dist: openpyxl
Provides-Extra: dev
Requires-Dist: check-manifest ; extra == 'dev'
Provides-Extra: test
Requires-Dist: coverage ; extra == 'test'
